<?xml version="1.0" ?>
<Gesture Name="triangle05" Subject="user2" Number="05">
    <Point X="248" Y="106" T="1677758895.137491"/>
    <Point X="246" Y="114" T="1677758895.1530519"/>
    <Point X="238" Y="131" T="1677758895.170523"/>
    <Point X="227" Y="155" T="1677758895.186375"/>
    <Point X="215" Y="184" T="1677758895.2034612"/>
    <Point X="202" Y="212" T="1677758895.2197278"/>
    <Point X="188" Y="240" T="1677758895.236348"/>
    <Point X="174" Y="270" T="1677758895.252778"/>
    <Point X="159" Y="301" T="1677758895.269464"/>
    <Point X="146" Y="330" T="1677758895.286158"/>
    <Point X="134" Y="358" T="1677758895.3028421"/>
    <Point X="125" Y="378" T="1677758895.319579"/>
    <Point X="119" Y="393" T="1677758895.336273"/>
    <Point X="114" Y="405" T="1677758895.3530629"/>
    <Point X="112" Y="411" T="1677758895.369687"/>
    <Point X="111" Y="414" T="1677758895.3863318"/>
    <Point X="111" Y="415" T="1677758895.403313"/>
    <Point X="115" Y="415" T="1677758895.5531032"/>
    <Point X="126" Y="413" T="1677758895.570113"/>
    <Point X="145" Y="408" T="1677758895.588481"/>
    <Point X="171" Y="402" T="1677758895.6036491"/>
    <Point X="196" Y="397" T="1677758895.619835"/>
    <Point X="220" Y="393" T="1677758895.6361852"/>
    <Point X="244" Y="389" T="1677758895.652823"/>
    <Point X="267" Y="387" T="1677758895.669558"/>
    <Point X="287" Y="385" T="1677758895.686264"/>
    <Point X="308" Y="382" T="1677758895.70307"/>
    <Point X="329" Y="379" T="1677758895.719775"/>
    <Point X="347" Y="376" T="1677758895.736345"/>
    <Point X="363" Y="373" T="1677758895.753545"/>
    <Point X="378" Y="370" T="1677758895.770022"/>
    <Point X="390" Y="368" T="1677758895.786918"/>
    <Point X="398" Y="366" T="1677758895.8034308"/>
    <Point X="404" Y="365" T="1677758895.825095"/>
    <Point X="409" Y="364" T="1677758895.840757"/>
    <Point X="414" Y="364" T="1677758895.856829"/>
    <Point X="419" Y="363" T="1677758895.8733492"/>
    <Point X="425" Y="362" T="1677758895.890063"/>
    <Point X="428" Y="362" T="1677758895.906146"/>
    <Point X="430" Y="362" T="1677758895.923872"/>
    <Point X="431" Y="362" T="1677758895.939611"/>
    <Point X="431" Y="361" T="1677758896.08779"/>
    <Point X="430" Y="360" T="1677758896.120321"/>
    <Point X="429" Y="359" T="1677758896.136203"/>
    <Point X="427" Y="356" T="1677758896.15693"/>
    <Point X="424" Y="353" T="1677758896.170177"/>
    <Point X="421" Y="349" T="1677758896.1864681"/>
    <Point X="417" Y="345" T="1677758896.203177"/>
    <Point X="413" Y="340" T="1677758896.2198558"/>
    <Point X="407" Y="335" T="1677758896.236591"/>
    <Point X="402" Y="329" T="1677758896.2533371"/>
    <Point X="397" Y="322" T="1677758896.269923"/>
    <Point X="391" Y="316" T="1677758896.286436"/>
    <Point X="385" Y="309" T="1677758896.302975"/>
    <Point X="378" Y="303" T="1677758896.3199391"/>
    <Point X="372" Y="296" T="1677758896.336641"/>
    <Point X="365" Y="290" T="1677758896.35326"/>
    <Point X="360" Y="285" T="1677758896.3700218"/>
    <Point X="356" Y="279" T="1677758896.3865228"/>
    <Point X="352" Y="274" T="1677758896.40314"/>
    <Point X="349" Y="269" T="1677758896.4199739"/>
    <Point X="346" Y="264" T="1677758896.43649"/>
    <Point X="344" Y="259" T="1677758896.4532402"/>
    <Point X="341" Y="254" T="1677758896.470054"/>
    <Point X="338" Y="249" T="1677758896.48686"/>
    <Point X="336" Y="244" T="1677758896.50302"/>
    <Point X="332" Y="239" T="1677758896.519788"/>
    <Point X="329" Y="233" T="1677758896.536473"/>
    <Point X="324" Y="226" T="1677758896.553169"/>
    <Point X="319" Y="218" T="1677758896.5698051"/>
    <Point X="315" Y="212" T="1677758896.586563"/>
    <Point X="312" Y="207" T="1677758896.6032481"/>
    <Point X="309" Y="202" T="1677758896.6198652"/>
    <Point X="306" Y="198" T="1677758896.63659"/>
    <Point X="304" Y="195" T="1677758896.652989"/>
    <Point X="301" Y="191" T="1677758896.670002"/>
    <Point X="298" Y="187" T="1677758896.68651"/>
    <Point X="295" Y="183" T="1677758896.703139"/>
    <Point X="292" Y="178" T="1677758896.719635"/>
    <Point X="289" Y="174" T="1677758896.736356"/>
    <Point X="287" Y="170" T="1677758896.75299"/>
    <Point X="285" Y="167" T="1677758896.76963"/>
    <Point X="283" Y="164" T="1677758896.7865899"/>
    <Point X="281" Y="162" T="1677758896.803363"/>
    <Point X="279" Y="159" T="1677758896.819892"/>
    <Point X="277" Y="156" T="1677758896.8365068"/>
    <Point X="275" Y="153" T="1677758896.853306"/>
    <Point X="272" Y="149" T="1677758896.869784"/>
    <Point X="269" Y="145" T="1677758896.886667"/>
    <Point X="267" Y="142" T="1677758896.903213"/>
    <Point X="264" Y="138" T="1677758896.91986"/>
    <Point X="262" Y="136" T="1677758896.936474"/>
    <Point X="260" Y="134" T="1677758896.953266"/>
    <Point X="259" Y="132" T="1677758896.969922"/>
    <Point X="257" Y="130" T="1677758896.98657"/>
    <Point X="255" Y="128" T="1677758897.0032399"/>
    <Point X="254" Y="127" T="1677758897.0197031"/>
    <Point X="251" Y="124" T="1677758897.036621"/>
    <Point X="247" Y="121" T="1677758897.053149"/>
    <Point X="244" Y="117" T="1677758897.069773"/>
    <Point X="241" Y="113" T="1677758897.086516"/>
    <Point X="238" Y="109" T="1677758897.103741"/>
    <Point X="237" Y="107" T="1677758897.119686"/>
    <Point X="236" Y="106" T="1677758897.1363258"/>
</Gesture>
