<?xml version="1.0" ?>
<Gesture Name="pigtail04" Subject="user01" Number="04">
    <Point X="171" Y="357" T="1681766921.391896"/>
    <Point X="171" Y="358" T="1681766921.424285"/>
    <Point X="172" Y="358" T="1681766921.4459388"/>
    <Point X="173" Y="358" T="1681766921.451852"/>
    <Point X="174" Y="358" T="1681766921.455412"/>
    <Point X="175" Y="357" T="1681766921.459736"/>
    <Point X="182" Y="355" T="1681766921.476819"/>
    <Point X="184" Y="354" T="1681766921.481982"/>
    <Point X="186" Y="352" T="1681766921.489044"/>
    <Point X="189" Y="351" T="1681766921.4902022"/>
    <Point X="191" Y="351" T="1681766921.4951"/>
    <Point X="194" Y="350" T="1681766921.496635"/>
    <Point X="199" Y="347" T="1681766921.506551"/>
    <Point X="202" Y="345" T="1681766921.5101929"/>
    <Point X="205" Y="344" T="1681766921.515729"/>
    <Point X="208" Y="342" T="1681766921.521743"/>
    <Point X="210" Y="341" T="1681766921.523176"/>
    <Point X="213" Y="339" T="1681766921.525562"/>
    <Point X="216" Y="338" T="1681766921.532546"/>
    <Point X="221" Y="335" T="1681766921.540222"/>
    <Point X="224" Y="334" T="1681766921.543518"/>
    <Point X="227" Y="332" T="1681766921.547126"/>
    <Point X="230" Y="330" T="1681766921.555074"/>
    <Point X="233" Y="328" T="1681766921.556256"/>
    <Point X="235" Y="326" T="1681766921.559227"/>
    <Point X="239" Y="325" T="1681766921.564001"/>
    <Point X="244" Y="321" T="1681766921.573171"/>
    <Point X="247" Y="319" T="1681766921.575352"/>
    <Point X="249" Y="317" T="1681766921.581294"/>
    <Point X="251" Y="315" T="1681766921.5886521"/>
    <Point X="254" Y="313" T="1681766921.5894861"/>
    <Point X="257" Y="312" T="1681766921.592464"/>
    <Point X="259" Y="310" T="1681766921.597615"/>
    <Point X="263" Y="306" T="1681766921.606646"/>
    <Point X="266" Y="303" T="1681766921.608248"/>
    <Point X="268" Y="301" T="1681766921.614578"/>
    <Point X="269" Y="299" T="1681766921.621878"/>
    <Point X="272" Y="296" T="1681766921.622009"/>
    <Point X="273" Y="294" T="1681766921.625632"/>
    <Point X="275" Y="292" T="1681766921.6328802"/>
    <Point X="277" Y="289" T="1681766921.639083"/>
    <Point X="278" Y="287" T="1681766921.6394901"/>
    <Point X="280" Y="285" T="1681766921.643487"/>
    <Point X="281" Y="282" T="1681766921.647891"/>
    <Point X="283" Y="280" T="1681766921.655046"/>
    <Point X="284" Y="277" T="1681766921.656699"/>
    <Point X="285" Y="275" T="1681766921.660404"/>
    <Point X="287" Y="272" T="1681766921.664381"/>
    <Point X="289" Y="267" T="1681766921.674011"/>
    <Point X="290" Y="265" T="1681766921.675871"/>
    <Point X="291" Y="263" T="1681766921.681155"/>
    <Point X="292" Y="260" T="1681766921.688969"/>
    <Point X="293" Y="258" T="1681766921.6895502"/>
    <Point X="294" Y="255" T="1681766921.693408"/>
    <Point X="295" Y="252" T="1681766921.697842"/>
    <Point X="296" Y="250" T="1681766921.701505"/>
    <Point X="296" Y="247" T="1681766921.707297"/>
    <Point X="297" Y="245" T="1681766921.7092988"/>
    <Point X="298" Y="243" T="1681766921.715195"/>
    <Point X="299" Y="241" T="1681766921.72354"/>
    <Point X="299" Y="238" T="1681766921.724681"/>
    <Point X="299" Y="237" T="1681766921.72612"/>
    <Point X="299" Y="235" T="1681766921.731043"/>
    <Point X="300" Y="231" T="1681766921.739754"/>
    <Point X="300" Y="229" T="1681766921.743541"/>
    <Point X="300" Y="227" T="1681766921.74797"/>
    <Point X="300" Y="225" T="1681766921.757633"/>
    <Point X="299" Y="217" T="1681766921.785567"/>
    <Point X="296" Y="215" T="1681766921.7947252"/>
    <Point X="293" Y="214" T="1681766921.806456"/>
    <Point X="289" Y="214" T="1681766921.822313"/>
    <Point X="288" Y="214" T="1681766921.822489"/>
    <Point X="287" Y="214" T="1681766921.824343"/>
    <Point X="285" Y="214" T="1681766921.82731"/>
    <Point X="284" Y="214" T="1681766921.832003"/>
    <Point X="281" Y="215" T="1681766921.8412402"/>
    <Point X="276" Y="217" T="1681766921.8555038"/>
    <Point X="274" Y="217" T="1681766921.858716"/>
    <Point X="272" Y="218" T="1681766921.859261"/>
    <Point X="270" Y="220" T="1681766921.864609"/>
    <Point X="266" Y="222" T="1681766921.873145"/>
    <Point X="265" Y="223" T="1681766921.879072"/>
    <Point X="259" Y="227" T="1681766921.889698"/>
    <Point X="258" Y="228" T="1681766921.8927832"/>
    <Point X="255" Y="230" T="1681766921.8977358"/>
    <Point X="253" Y="233" T="1681766921.907456"/>
    <Point X="249" Y="237" T="1681766921.91442"/>
    <Point X="247" Y="238" T="1681766921.922125"/>
    <Point X="246" Y="240" T="1681766921.922875"/>
    <Point X="243" Y="246" T="1681766921.93874"/>
    <Point X="241" Y="248" T="1681766921.9407492"/>
    <Point X="240" Y="251" T="1681766921.943604"/>
    <Point X="239" Y="253" T="1681766921.9477398"/>
    <Point X="238" Y="256" T="1681766921.956505"/>
    <Point X="238" Y="258" T="1681766921.956906"/>
    <Point X="236" Y="260" T="1681766921.9596539"/>
    <Point X="236" Y="262" T="1681766921.964606"/>
    <Point X="235" Y="264" T="1681766921.972221"/>
    <Point X="235" Y="267" T="1681766921.973289"/>
    <Point X="234" Y="270" T="1681766921.976156"/>
    <Point X="234" Y="272" T="1681766921.981993"/>
    <Point X="233" Y="275" T="1681766921.989941"/>
    <Point X="233" Y="285" T="1681766922.001633"/>
    <Point X="233" Y="287" T="1681766922.006335"/>
    <Point X="233" Y="289" T="1681766922.009941"/>
    <Point X="233" Y="292" T="1681766922.014246"/>
    <Point X="235" Y="295" T="1681766922.0221682"/>
    <Point X="235" Y="297" T="1681766922.023266"/>
    <Point X="236" Y="300" T="1681766922.026456"/>
    <Point X="237" Y="302" T="1681766922.0311308"/>
    <Point X="239" Y="306" T="1681766922.040137"/>
    <Point X="240" Y="309" T="1681766922.043647"/>
    <Point X="243" Y="311" T="1681766922.0480058"/>
    <Point X="246" Y="314" T="1681766922.0566988"/>
    <Point X="247" Y="316" T="1681766922.060595"/>
    <Point X="250" Y="318" T="1681766922.0658062"/>
    <Point X="251" Y="320" T="1681766922.068116"/>
    <Point X="254" Y="321" T="1681766922.072937"/>
    <Point X="257" Y="322" T="1681766922.076391"/>
    <Point X="259" Y="323" T="1681766922.081017"/>
    <Point X="262" Y="325" T="1681766922.089121"/>
    <Point X="265" Y="326" T="1681766922.089507"/>
    <Point X="268" Y="327" T="1681766922.09197"/>
    <Point X="271" Y="328" T="1681766922.097207"/>
    <Point X="274" Y="329" T="1681766922.1016011"/>
    <Point X="277" Y="330" T="1681766922.106614"/>
    <Point X="281" Y="331" T="1681766922.109875"/>
    <Point X="284" Y="332" T="1681766922.114763"/>
    <Point X="288" Y="332" T="1681766922.118199"/>
    <Point X="292" Y="333" T="1681766922.123596"/>
    <Point X="296" Y="334" T="1681766922.1285062"/>
    <Point X="300" Y="334" T="1681766922.1302469"/>
    <Point X="308" Y="335" T="1681766922.139585"/>
    <Point X="313" Y="335" T="1681766922.1424232"/>
    <Point X="318" Y="335" T="1681766922.147391"/>
    <Point X="322" Y="336" T="1681766922.1560059"/>
    <Point X="326" Y="336" T="1681766922.156706"/>
    <Point X="330" Y="336" T="1681766922.1593869"/>
    <Point X="335" Y="336" T="1681766922.164583"/>
    <Point X="340" Y="336" T="1681766922.172705"/>
    <Point X="345" Y="336" T="1681766922.173066"/>
    <Point X="348" Y="336" T="1681766922.177238"/>
    <Point X="352" Y="335" T="1681766922.180613"/>
    <Point X="361" Y="335" T="1681766922.1900532"/>
    <Point X="366" Y="334" T="1681766922.194096"/>
    <Point X="370" Y="333" T="1681766922.1979148"/>
    <Point X="378" Y="332" T="1681766922.206885"/>
    <Point X="381" Y="331" T="1681766922.209381"/>
    <Point X="385" Y="330" T="1681766922.21505"/>
    <Point X="388" Y="330" T="1681766922.218261"/>
    <Point X="391" Y="328" T="1681766922.2229571"/>
    <Point X="394" Y="327" T="1681766922.225832"/>
    <Point X="396" Y="327" T="1681766922.231023"/>
    <Point X="398" Y="326" T="1681766922.239488"/>
    <Point X="400" Y="325" T="1681766922.241291"/>
    <Point X="401" Y="323" T="1681766922.2429178"/>
    <Point X="402" Y="322" T="1681766922.247509"/>
    <Point X="404" Y="321" T="1681766922.2562199"/>
    <Point X="145" Y="376" T="1681766923.906284"/>
    <Point X="144" Y="376" T="1681766923.9112"/>
    <Point X="144" Y="377" T="1681766923.9219918"/>
    <Point X="144" Y="378" T="1681766923.930739"/>
    <Point X="145" Y="378" T="1681766923.949353"/>
    <Point X="146" Y="378" T="1681766923.9617941"/>
    <Point X="148" Y="378" T="1681766923.963684"/>
    <Point X="152" Y="377" T="1681766923.981806"/>
    <Point X="153" Y="377" T="1681766923.99014"/>
    <Point X="155" Y="377" T="1681766923.9944131"/>
    <Point X="156" Y="377" T="1681766923.997451"/>
    <Point X="158" Y="376" T="1681766924.006143"/>
    <Point X="160" Y="376" T="1681766924.006358"/>
    <Point X="172" Y="372" T="1681766924.035703"/>
    <Point X="175" Y="371" T="1681766924.0399559"/>
    <Point X="177" Y="370" T="1681766924.042836"/>
    <Point X="179" Y="369" T="1681766924.0486882"/>
    <Point X="183" Y="367" T="1681766924.055868"/>
    <Point X="186" Y="366" T="1681766924.056155"/>
    <Point X="189" Y="365" T="1681766924.059892"/>
    <Point X="191" Y="363" T="1681766924.065692"/>
    <Point X="194" Y="362" T="1681766924.0722911"/>
    <Point X="197" Y="360" T="1681766924.07286"/>
    <Point X="201" Y="359" T="1681766924.0766551"/>
    <Point X="203" Y="357" T="1681766924.081038"/>
    <Point X="206" Y="356" T="1681766924.0846431"/>
    <Point X="220" Y="347" T="1681766924.107698"/>
    <Point X="223" Y="345" T="1681766924.112312"/>
    <Point X="225" Y="344" T="1681766924.114105"/>
    <Point X="228" Y="342" T="1681766924.1179872"/>
    <Point X="233" Y="338" T="1681766924.132237"/>
    <Point X="235" Y="337" T="1681766924.132468"/>
    <Point X="240" Y="333" T="1681766924.139683"/>
    <Point X="260" Y="313" T="1681766924.1793878"/>
    <Point X="265" Y="308" T="1681766924.1834931"/>
    <Point X="270" Y="300" T="1681766924.1975338"/>
    <Point X="272" Y="297" T="1681766924.198171"/>
    <Point X="276" Y="292" T="1681766924.207564"/>
    <Point X="277" Y="290" T="1681766924.209517"/>
    <Point X="278" Y="287" T="1681766924.213994"/>
    <Point X="280" Y="285" T="1681766924.217943"/>
    <Point X="281" Y="282" T="1681766924.223868"/>
    <Point X="283" Y="279" T="1681766924.2269351"/>
    <Point X="288" Y="268" T="1681766924.24601"/>
    <Point X="289" Y="266" T="1681766924.249683"/>
    <Point X="293" Y="258" T="1681766924.2669709"/>
    <Point X="294" Y="256" T="1681766924.2680378"/>
    <Point X="296" Y="253" T="1681766924.2723148"/>
    <Point X="298" Y="248" T="1681766924.2816992"/>
    <Point X="299" Y="246" T="1681766924.28203"/>
    <Point X="299" Y="244" T="1681766924.289133"/>
    <Point X="300" Y="241" T="1681766924.292"/>
    <Point X="300" Y="239" T="1681766924.295805"/>
    <Point X="302" Y="238" T="1681766924.296452"/>
    <Point X="302" Y="233" T="1681766924.306751"/>
    <Point X="303" Y="232" T="1681766924.30947"/>
    <Point X="303" Y="230" T="1681766924.315114"/>
    <Point X="303" Y="227" T="1681766924.322473"/>
    <Point X="303" Y="225" T="1681766924.326816"/>
    <Point X="303" Y="223" T="1681766924.331563"/>
    <Point X="302" Y="222" T="1681766924.339007"/>
    <Point X="302" Y="220" T="1681766924.339353"/>
    <Point X="301" Y="220" T="1681766924.342494"/>
    <Point X="300" Y="218" T="1681766924.3475132"/>
    <Point X="300" Y="217" T="1681766924.35141"/>
    <Point X="299" Y="216" T="1681766924.356717"/>
    <Point X="298" Y="215" T="1681766924.359204"/>
    <Point X="297" Y="215" T="1681766924.364077"/>
    <Point X="296" Y="214" T="1681766924.3680372"/>
    <Point X="295" Y="214" T="1681766924.373302"/>
    <Point X="294" Y="213" T="1681766924.3755178"/>
    <Point X="293" Y="213" T="1681766924.380735"/>
    <Point X="292" Y="213" T="1681766924.389935"/>
    <Point X="291" Y="213" T="1681766924.391341"/>
    <Point X="289" Y="213" T="1681766924.392614"/>
    <Point X="288" Y="213" T="1681766924.3977962"/>
    <Point X="287" Y="213" T="1681766924.401479"/>
    <Point X="286" Y="213" T="1681766924.4063401"/>
    <Point X="285" Y="213" T="1681766924.411264"/>
    <Point X="284" Y="213" T="1681766924.41403"/>
    <Point X="281" Y="214" T="1681766924.423638"/>
    <Point X="279" Y="214" T="1681766924.426566"/>
    <Point X="277" Y="215" T="1681766924.430788"/>
    <Point X="276" Y="215" T="1681766924.434768"/>
    <Point X="274" Y="216" T="1681766924.439316"/>
    <Point X="272" Y="217" T="1681766924.4419699"/>
    <Point X="270" Y="218" T="1681766924.447156"/>
    <Point X="266" Y="220" T="1681766924.456928"/>
    <Point X="265" Y="221" T="1681766924.459624"/>
    <Point X="262" Y="222" T="1681766924.4641678"/>
    <Point X="261" Y="224" T="1681766924.46815"/>
    <Point X="258" Y="225" T="1681766924.4727721"/>
    <Point X="257" Y="227" T="1681766924.47546"/>
    <Point X="254" Y="227" T="1681766924.480713"/>
    <Point X="251" Y="230" T="1681766924.490405"/>
    <Point X="250" Y="232" T="1681766924.493189"/>
    <Point X="248" Y="233" T="1681766924.498354"/>
    <Point X="246" Y="235" T="1681766924.501398"/>
    <Point X="244" Y="236" T="1681766924.506468"/>
    <Point X="243" Y="238" T="1681766924.511487"/>
    <Point X="242" Y="239" T="1681766924.513435"/>
    <Point X="240" Y="242" T="1681766924.524009"/>
    <Point X="239" Y="245" T="1681766924.525582"/>
    <Point X="238" Y="246" T="1681766924.531191"/>
    <Point X="237" Y="248" T="1681766924.538799"/>
    <Point X="236" Y="250" T="1681766924.5400221"/>
    <Point X="235" Y="252" T="1681766924.541867"/>
    <Point X="231" Y="267" T="1681766924.573652"/>
    <Point X="230" Y="270" T="1681766924.5756218"/>
    <Point X="229" Y="271" T="1681766924.582508"/>
    <Point X="228" Y="276" T="1681766924.590015"/>
    <Point X="228" Y="278" T="1681766924.593173"/>
    <Point X="228" Y="281" T="1681766924.598046"/>
    <Point X="228" Y="286" T="1681766924.607021"/>
    <Point X="228" Y="288" T="1681766924.608866"/>
    <Point X="228" Y="295" T="1681766924.62332"/>
    <Point X="228" Y="298" T="1681766924.627531"/>
    <Point X="228" Y="301" T="1681766924.630639"/>
    <Point X="229" Y="306" T="1681766924.63995"/>
    <Point X="229" Y="308" T="1681766924.642344"/>
    <Point X="231" Y="310" T="1681766924.646658"/>
    <Point X="232" Y="313" T="1681766924.65571"/>
    <Point X="232" Y="315" T="1681766924.6579242"/>
    <Point X="233" Y="317" T="1681766924.66189"/>
    <Point X="235" Y="319" T="1681766924.6739259"/>
    <Point X="238" Y="323" T="1681766924.67406"/>
    <Point X="239" Y="326" T="1681766924.679683"/>
    <Point X="241" Y="327" T="1681766924.681769"/>
    <Point X="243" Y="330" T="1681766924.6900501"/>
    <Point X="244" Y="332" T="1681766924.690637"/>
    <Point X="246" Y="333" T="1681766924.693016"/>
    <Point X="248" Y="335" T="1681766924.697043"/>
    <Point X="250" Y="337" T="1681766924.701589"/>
    <Point X="253" Y="338" T="1681766924.7062368"/>
    <Point X="255" Y="340" T="1681766924.708864"/>
    <Point X="258" Y="341" T="1681766924.714475"/>
    <Point X="261" Y="343" T="1681766924.718187"/>
    <Point X="263" Y="345" T="1681766924.722898"/>
    <Point X="266" Y="346" T="1681766924.725451"/>
    <Point X="269" Y="347" T="1681766924.7307022"/>
    <Point X="274" Y="350" T="1681766924.73946"/>
    <Point X="277" Y="351" T="1681766924.74294"/>
    <Point X="283" Y="352" T="1681766924.756136"/>
    <Point X="286" Y="353" T="1681766924.756309"/>
    <Point X="289" Y="354" T="1681766924.75868"/>
    <Point X="292" Y="354" T="1681766924.7638469"/>
    <Point X="296" Y="355" T="1681766924.772794"/>
    <Point X="300" Y="355" T="1681766924.772964"/>
    <Point X="304" Y="355" T="1681766924.7757828"/>
    <Point X="307" Y="355" T="1681766924.7798882"/>
    <Point X="311" Y="355" T="1681766924.789162"/>
    <Point X="315" Y="355" T="1681766924.789523"/>
    <Point X="319" Y="355" T="1681766924.792054"/>
    <Point X="323" Y="355" T="1681766924.797683"/>
    <Point X="328" Y="355" T="1681766924.805989"/>
    <Point X="332" Y="355" T="1681766924.806378"/>
    <Point X="336" Y="354" T="1681766924.8090901"/>
    <Point X="341" Y="354" T="1681766924.815001"/>
    <Point X="345" Y="353" T="1681766924.8225548"/>
    <Point X="349" Y="352" T="1681766924.822983"/>
    <Point X="354" Y="351" T="1681766924.82685"/>
    <Point X="358" Y="351" T="1681766924.8310661"/>
    <Point X="363" Y="350" T="1681766924.834882"/>
    <Point X="367" Y="348" T="1681766924.8397079"/>
    <Point X="371" Y="347" T="1681766924.842004"/>
    <Point X="376" Y="346" T="1681766924.848601"/>
    <Point X="381" Y="345" T="1681766924.856163"/>
    <Point X="385" Y="344" T="1681766924.8564858"/>
    <Point X="389" Y="343" T="1681766924.858916"/>
    <Point X="392" Y="342" T="1681766924.864371"/>
    <Point X="396" Y="341" T="1681766924.873159"/>
    <Point X="399" Y="340" T="1681766924.873527"/>
    <Point X="402" Y="339" T="1681766924.875556"/>
    <Point X="405" Y="338" T="1681766924.88111"/>
    <Point X="406" Y="338" T="1681766924.8848581"/>
    <Point X="408" Y="337" T="1681766924.889676"/>
    <Point X="410" Y="337" T="1681766924.8923688"/>
    <Point X="411" Y="336" T="1681766924.897701"/>
    <Point X="413" Y="335" T="1681766924.9065092"/>
</Gesture>
