<?xml version="1.0" ?>
<Gesture Name="x07" Subject="user01" Number="07">
    <Point X="189" Y="169" T="1681766151.1932569"/>
    <Point X="188" Y="169" T="1681766151.197411"/>
    <Point X="187" Y="169" T="1681766151.204821"/>
    <Point X="187" Y="170" T="1681766151.220974"/>
    <Point X="187" Y="171" T="1681766151.237835"/>
    <Point X="188" Y="171" T="1681766151.240404"/>
    <Point X="189" Y="171" T="1681766151.248876"/>
    <Point X="189" Y="172" T="1681766151.2546592"/>
    <Point X="190" Y="172" T="1681766151.25562"/>
    <Point X="190" Y="173" T="1681766151.269681"/>
    <Point X="191" Y="174" T="1681766151.2707012"/>
    <Point X="191" Y="175" T="1681766151.274865"/>
    <Point X="192" Y="176" T="1681766151.280428"/>
    <Point X="193" Y="177" T="1681766151.282926"/>
    <Point X="194" Y="177" T="1681766151.286954"/>
    <Point X="194" Y="178" T="1681766151.294324"/>
    <Point X="194" Y="179" T="1681766151.297421"/>
    <Point X="195" Y="180" T="1681766151.299319"/>
    <Point X="195" Y="181" T="1681766151.3045068"/>
    <Point X="197" Y="182" T="1681766151.306518"/>
    <Point X="197" Y="183" T="1681766151.3135529"/>
    <Point X="198" Y="184" T="1681766151.316135"/>
    <Point X="199" Y="186" T="1681766151.320492"/>
    <Point X="200" Y="187" T="1681766151.321702"/>
    <Point X="201" Y="188" T="1681766151.329397"/>
    <Point X="202" Y="189" T="1681766151.3303611"/>
    <Point X="203" Y="190" T="1681766151.3379378"/>
    <Point X="204" Y="191" T="1681766151.338478"/>
    <Point X="205" Y="192" T="1681766151.346069"/>
    <Point X="206" Y="193" T="1681766151.347508"/>
    <Point X="208" Y="195" T="1681766151.354698"/>
    <Point X="209" Y="196" T="1681766151.355679"/>
    <Point X="213" Y="201" T="1681766151.370903"/>
    <Point X="215" Y="202" T="1681766151.372402"/>
    <Point X="216" Y="203" T="1681766151.379439"/>
    <Point X="217" Y="205" T="1681766151.382154"/>
    <Point X="219" Y="206" T="1681766151.388024"/>
    <Point X="220" Y="208" T="1681766151.3887072"/>
    <Point X="223" Y="209" T="1681766151.3965042"/>
    <Point X="224" Y="211" T="1681766151.3979788"/>
    <Point X="225" Y="213" T="1681766151.404375"/>
    <Point X="227" Y="214" T="1681766151.406707"/>
    <Point X="228" Y="215" T="1681766151.41391"/>
    <Point X="230" Y="217" T="1681766151.415565"/>
    <Point X="232" Y="220" T="1681766151.420504"/>
    <Point X="233" Y="221" T="1681766151.4359019"/>
    <Point X="236" Y="225" T="1681766151.43602"/>
    <Point X="238" Y="226" T="1681766151.437448"/>
    <Point X="239" Y="228" T="1681766151.438412"/>
    <Point X="242" Y="230" T="1681766151.446958"/>
    <Point X="243" Y="232" T="1681766151.4477"/>
    <Point X="244" Y="233" T="1681766151.455296"/>
    <Point X="246" Y="235" T="1681766151.456257"/>
    <Point X="247" Y="237" T="1681766151.46271"/>
    <Point X="248" Y="238" T="1681766151.46444"/>
    <Point X="250" Y="240" T="1681766151.4715142"/>
    <Point X="252" Y="241" T="1681766151.473106"/>
    <Point X="254" Y="243" T="1681766151.4791548"/>
    <Point X="255" Y="245" T="1681766151.48002"/>
    <Point X="257" Y="246" T="1681766151.4877288"/>
    <Point X="258" Y="248" T="1681766151.4901068"/>
    <Point X="259" Y="251" T="1681766151.495368"/>
    <Point X="261" Y="252" T="1681766151.4968011"/>
    <Point X="262" Y="253" T="1681766151.503745"/>
    <Point X="263" Y="255" T="1681766151.506185"/>
    <Point X="266" Y="258" T="1681766151.514575"/>
    <Point X="268" Y="261" T="1681766151.521395"/>
    <Point X="269" Y="262" T="1681766151.521664"/>
    <Point X="270" Y="263" T="1681766151.532254"/>
    <Point X="271" Y="265" T="1681766151.5325089"/>
    <Point X="273" Y="267" T="1681766151.537827"/>
    <Point X="273" Y="268" T="1681766151.539028"/>
    <Point X="275" Y="270" T="1681766151.545585"/>
    <Point X="277" Y="271" T="1681766151.546967"/>
    <Point X="277" Y="273" T="1681766151.5540538"/>
    <Point X="278" Y="275" T="1681766151.556774"/>
    <Point X="281" Y="277" T="1681766151.564585"/>
    <Point X="283" Y="279" T="1681766151.571552"/>
    <Point X="284" Y="280" T="1681766151.572117"/>
    <Point X="284" Y="282" T="1681766151.579896"/>
    <Point X="285" Y="283" T="1681766151.582384"/>
    <Point X="287" Y="284" T="1681766151.587074"/>
    <Point X="288" Y="286" T="1681766151.588775"/>
    <Point X="289" Y="287" T="1681766151.5969112"/>
    <Point X="290" Y="288" T="1681766151.604815"/>
    <Point X="291" Y="289" T="1681766151.60495"/>
    <Point X="292" Y="290" T="1681766151.6054258"/>
    <Point X="294" Y="293" T="1681766151.6156642"/>
    <Point X="296" Y="295" T="1681766151.620533"/>
    <Point X="298" Y="296" T="1681766151.629031"/>
    <Point X="299" Y="298" T="1681766151.630551"/>
    <Point X="300" Y="300" T="1681766151.6389172"/>
    <Point X="302" Y="302" T="1681766151.6460009"/>
    <Point X="303" Y="303" T="1681766151.653491"/>
    <Point X="304" Y="305" T="1681766151.6579342"/>
    <Point X="305" Y="306" T="1681766151.662721"/>
    <Point X="307" Y="309" T="1681766151.6711712"/>
    <Point X="307" Y="310" T="1681766151.6725929"/>
    <Point X="307" Y="311" T="1681766151.677567"/>
    <Point X="308" Y="312" T="1681766151.68261"/>
    <Point X="309" Y="313" T="1681766151.687167"/>
    <Point X="310" Y="314" T="1681766151.6902559"/>
    <Point X="310" Y="315" T="1681766151.694808"/>
    <Point X="311" Y="316" T="1681766151.7047281"/>
    <Point X="311" Y="317" T="1681766151.7048619"/>
    <Point X="312" Y="318" T="1681766151.706165"/>
    <Point X="312" Y="320" T="1681766151.713768"/>
    <Point X="313" Y="320" T="1681766151.714077"/>
    <Point X="314" Y="321" T="1681766151.720813"/>
    <Point X="314" Y="322" T="1681766151.723009"/>
    <Point X="315" Y="323" T="1681766151.729154"/>
    <Point X="315" Y="324" T="1681766151.731435"/>
    <Point X="316" Y="325" T="1681766151.738556"/>
    <Point X="317" Y="326" T="1681766151.738848"/>
    <Point X="318" Y="326" T="1681766151.744565"/>
    <Point X="318" Y="327" T="1681766151.749355"/>
    <Point X="319" Y="328" T="1681766151.756659"/>
    <Point X="319" Y="329" T="1681766151.7611651"/>
    <Point X="319" Y="330" T="1681766151.7660658"/>
    <Point X="320" Y="330" T="1681766151.770163"/>
    <Point X="321" Y="331" T="1681766151.773012"/>
    <Point X="321" Y="332" T="1681766151.780044"/>
    <Point X="322" Y="332" T="1681766151.789206"/>
    <Point X="322" Y="333" T="1681766151.794312"/>
    <Point X="322" Y="332" T="1681766151.8695848"/>
    <Point X="322" Y="331" T="1681766151.879672"/>
    <Point X="322" Y="330" T="1681766151.893887"/>
    <Point X="322" Y="328" T="1681766151.895236"/>
    <Point X="322" Y="327" T="1681766151.903678"/>
    <Point X="322" Y="326" T="1681766151.906925"/>
    <Point X="322" Y="325" T="1681766151.91605"/>
    <Point X="322" Y="323" T="1681766151.920481"/>
    <Point X="322" Y="322" T="1681766151.9234612"/>
    <Point X="321" Y="321" T="1681766151.932907"/>
    <Point X="321" Y="320" T="1681766151.937184"/>
    <Point X="321" Y="318" T="1681766151.93959"/>
    <Point X="321" Y="317" T="1681766151.9458492"/>
    <Point X="321" Y="313" T="1681766151.958715"/>
    <Point X="320" Y="312" T="1681766151.9617732"/>
    <Point X="320" Y="311" T="1681766151.9706109"/>
    <Point X="319" Y="309" T="1681766151.970782"/>
    <Point X="319" Y="307" T="1681766151.973442"/>
    <Point X="319" Y="306" T="1681766151.9782112"/>
    <Point X="319" Y="304" T="1681766151.982708"/>
    <Point X="318" Y="302" T="1681766151.987932"/>
    <Point X="318" Y="301" T="1681766151.990491"/>
    <Point X="318" Y="300" T="1681766151.994391"/>
    <Point X="318" Y="298" T="1681766152.005316"/>
    <Point X="317" Y="295" T="1681766152.0054889"/>
    <Point X="317" Y="293" T="1681766152.0116549"/>
    <Point X="317" Y="292" T="1681766152.0132139"/>
    <Point X="317" Y="290" T="1681766152.021503"/>
    <Point X="316" Y="289" T="1681766152.022563"/>
    <Point X="316" Y="287" T="1681766152.028772"/>
    <Point X="315" Y="286" T="1681766152.030236"/>
    <Point X="315" Y="284" T="1681766152.038018"/>
    <Point X="315" Y="283" T="1681766152.039217"/>
    <Point X="314" Y="281" T="1681766152.0455658"/>
    <Point X="314" Y="279" T="1681766152.0540411"/>
    <Point X="314" Y="277" T="1681766152.054188"/>
    <Point X="314" Y="276" T="1681766152.056648"/>
    <Point X="314" Y="275" T="1681766152.061652"/>
    <Point X="314" Y="273" T="1681766152.064223"/>
    <Point X="313" Y="271" T="1681766152.07146"/>
    <Point X="313" Y="270" T="1681766152.07318"/>
    <Point X="312" Y="268" T="1681766152.077921"/>
    <Point X="312" Y="264" T="1681766152.088114"/>
    <Point X="312" Y="263" T="1681766152.090257"/>
    <Point X="312" Y="261" T="1681766152.09467"/>
    <Point X="312" Y="260" T="1681766152.104102"/>
    <Point X="311" Y="258" T="1681766152.104272"/>
    <Point X="311" Y="257" T="1681766152.106111"/>
    <Point X="311" Y="255" T="1681766152.111954"/>
    <Point X="311" Y="253" T="1681766152.116224"/>
    <Point X="311" Y="252" T="1681766152.1208022"/>
    <Point X="311" Y="251" T="1681766152.123497"/>
    <Point X="311" Y="249" T="1681766152.1292942"/>
    <Point X="311" Y="247" T="1681766152.1310349"/>
    <Point X="311" Y="246" T="1681766152.138137"/>
    <Point X="311" Y="245" T="1681766152.139013"/>
    <Point X="310" Y="242" T="1681766152.14506"/>
    <Point X="310" Y="241" T="1681766152.14946"/>
    <Point X="310" Y="239" T="1681766152.153943"/>
    <Point X="310" Y="238" T="1681766152.156414"/>
    <Point X="310" Y="236" T="1681766152.1613178"/>
    <Point X="310" Y="235" T="1681766152.1661398"/>
    <Point X="310" Y="233" T="1681766152.170634"/>
    <Point X="310" Y="231" T="1681766152.1720698"/>
    <Point X="309" Y="230" T="1681766152.1790988"/>
    <Point X="309" Y="228" T="1681766152.1808288"/>
    <Point X="309" Y="227" T="1681766152.1881652"/>
    <Point X="309" Y="225" T="1681766152.189943"/>
    <Point X="308" Y="223" T="1681766152.19502"/>
    <Point X="308" Y="221" T="1681766152.196474"/>
    <Point X="308" Y="220" T="1681766152.205029"/>
    <Point X="308" Y="218" T="1681766152.205701"/>
    <Point X="308" Y="217" T="1681766152.211605"/>
    <Point X="308" Y="215" T="1681766152.2210891"/>
    <Point X="307" Y="213" T="1681766152.2212749"/>
    <Point X="307" Y="212" T="1681766152.2224262"/>
    <Point X="307" Y="211" T="1681766152.228502"/>
    <Point X="307" Y="209" T="1681766152.2306528"/>
    <Point X="307" Y="206" T="1681766152.2385159"/>
    <Point X="306" Y="203" T="1681766152.245376"/>
    <Point X="306" Y="202" T="1681766152.246628"/>
    <Point X="306" Y="201" T="1681766152.254633"/>
    <Point X="306" Y="198" T="1681766152.256282"/>
    <Point X="306" Y="197" T="1681766152.263236"/>
    <Point X="305" Y="193" T="1681766152.271457"/>
    <Point X="305" Y="192" T="1681766152.272937"/>
    <Point X="305" Y="190" T="1681766152.280427"/>
    <Point X="304" Y="188" T="1681766152.282888"/>
    <Point X="304" Y="187" T="1681766152.287404"/>
    <Point X="304" Y="186" T="1681766152.289568"/>
    <Point X="304" Y="184" T="1681766152.2945778"/>
    <Point X="304" Y="183" T="1681766152.2994409"/>
    <Point X="304" Y="181" T="1681766152.303822"/>
    <Point X="304" Y="180" T="1681766152.311295"/>
    <Point X="304" Y="178" T="1681766152.311597"/>
    <Point X="304" Y="177" T="1681766152.314406"/>
    <Point X="304" Y="175" T="1681766152.320628"/>
    <Point X="304" Y="173" T="1681766152.322361"/>
    <Point X="304" Y="172" T="1681766152.328528"/>
    <Point X="304" Y="171" T="1681766152.331062"/>
    <Point X="304" Y="168" T="1681766152.339531"/>
    <Point X="304" Y="167" T="1681766152.345838"/>
    <Point X="304" Y="165" T="1681766152.347522"/>
    <Point X="304" Y="164" T="1681766152.3547678"/>
    <Point X="304" Y="163" T="1681766152.35678"/>
    <Point X="304" Y="162" T="1681766152.361452"/>
    <Point X="304" Y="161" T="1681766152.363727"/>
    <Point X="304" Y="160" T="1681766152.3717601"/>
    <Point X="304" Y="159" T="1681766152.372092"/>
    <Point X="304" Y="158" T="1681766152.378264"/>
    <Point X="304" Y="157" T="1681766152.38271"/>
    <Point X="304" Y="155" T="1681766152.389836"/>
    <Point X="304" Y="154" T="1681766152.394762"/>
    <Point X="304" Y="153" T="1681766152.3973088"/>
    <Point X="304" Y="152" T="1681766152.405737"/>
    <Point X="303" Y="150" T="1681766152.4299588"/>
    <Point X="303" Y="148" T="1681766152.4406679"/>
    <Point X="302" Y="148" T="1681766152.447204"/>
    <Point X="302" Y="147" T="1681766152.456369"/>
    <Point X="301" Y="147" T="1681766152.48302"/>
    <Point X="300" Y="147" T="1681766152.5037608"/>
    <Point X="300" Y="148" T="1681766152.514095"/>
    <Point X="299" Y="149" T="1681766152.523408"/>
    <Point X="299" Y="150" T="1681766152.5290802"/>
    <Point X="299" Y="151" T="1681766152.530582"/>
    <Point X="298" Y="152" T="1681766152.539714"/>
    <Point X="298" Y="153" T="1681766152.549401"/>
    <Point X="297" Y="155" T="1681766152.554259"/>
    <Point X="296" Y="155" T="1681766152.555764"/>
    <Point X="296" Y="156" T="1681766152.562034"/>
    <Point X="296" Y="157" T="1681766152.56607"/>
    <Point X="295" Y="158" T="1681766152.572147"/>
    <Point X="294" Y="160" T="1681766152.579058"/>
    <Point X="293" Y="161" T="1681766152.580735"/>
    <Point X="293" Y="162" T="1681766152.5885382"/>
    <Point X="292" Y="163" T="1681766152.589189"/>
    <Point X="291" Y="165" T="1681766152.599468"/>
    <Point X="290" Y="166" T="1681766152.604373"/>
    <Point X="289" Y="167" T="1681766152.60561"/>
    <Point X="288" Y="169" T="1681766152.611954"/>
    <Point X="288" Y="170" T="1681766152.613961"/>
    <Point X="285" Y="173" T="1681766152.622132"/>
    <Point X="284" Y="175" T="1681766152.628445"/>
    <Point X="284" Y="177" T="1681766152.630507"/>
    <Point X="283" Y="178" T="1681766152.6386602"/>
    <Point X="281" Y="180" T="1681766152.639893"/>
    <Point X="280" Y="182" T="1681766152.64498"/>
    <Point X="279" Y="183" T="1681766152.647541"/>
    <Point X="277" Y="187" T="1681766152.655437"/>
    <Point X="276" Y="188" T="1681766152.662282"/>
    <Point X="274" Y="189" T="1681766152.6661272"/>
    <Point X="273" Y="191" T="1681766152.67156"/>
    <Point X="272" Y="193" T="1681766152.6736372"/>
    <Point X="270" Y="195" T="1681766152.678386"/>
    <Point X="269" Y="196" T="1681766152.687784"/>
    <Point X="268" Y="198" T="1681766152.687962"/>
    <Point X="266" Y="200" T="1681766152.690102"/>
    <Point X="265" Y="202" T="1681766152.69528"/>
    <Point X="264" Y="204" T="1681766152.699525"/>
    <Point X="262" Y="206" T="1681766152.704888"/>
    <Point X="262" Y="208" T="1681766152.7064378"/>
    <Point X="261" Y="210" T="1681766152.71184"/>
    <Point X="259" Y="211" T="1681766152.7139452"/>
    <Point X="258" Y="213" T="1681766152.722024"/>
    <Point X="257" Y="215" T="1681766152.7237608"/>
    <Point X="256" Y="217" T="1681766152.728201"/>
    <Point X="255" Y="218" T="1681766152.730355"/>
    <Point X="253" Y="222" T="1681766152.7394419"/>
    <Point X="252" Y="224" T="1681766152.745436"/>
    <Point X="251" Y="226" T="1681766152.7476218"/>
    <Point X="250" Y="229" T="1681766152.755487"/>
    <Point X="248" Y="231" T="1681766152.76219"/>
    <Point X="247" Y="234" T="1681766152.771295"/>
    <Point X="247" Y="236" T="1681766152.772529"/>
    <Point X="246" Y="237" T="1681766152.777322"/>
    <Point X="245" Y="238" T="1681766152.7876348"/>
    <Point X="244" Y="240" T="1681766152.788042"/>
    <Point X="243" Y="241" T="1681766152.788704"/>
    <Point X="243" Y="243" T="1681766152.79532"/>
    <Point X="241" Y="246" T="1681766152.8046231"/>
    <Point X="240" Y="248" T="1681766152.807374"/>
    <Point X="239" Y="250" T="1681766152.814186"/>
    <Point X="238" Y="252" T="1681766152.814461"/>
    <Point X="237" Y="253" T="1681766152.822079"/>
    <Point X="236" Y="255" T="1681766152.823165"/>
    <Point X="235" Y="257" T="1681766152.828827"/>
    <Point X="233" Y="260" T="1681766152.8388412"/>
    <Point X="232" Y="262" T="1681766152.839356"/>
    <Point X="231" Y="264" T="1681766152.845226"/>
    <Point X="229" Y="265" T="1681766152.849508"/>
    <Point X="228" Y="267" T="1681766152.854563"/>
    <Point X="228" Y="269" T="1681766152.8571122"/>
    <Point X="227" Y="270" T="1681766152.86223"/>
    <Point X="225" Y="272" T="1681766152.864275"/>
    <Point X="224" Y="274" T="1681766152.872211"/>
    <Point X="224" Y="276" T="1681766152.872512"/>
    <Point X="223" Y="277" T="1681766152.878659"/>
    <Point X="221" Y="279" T="1681766152.882698"/>
    <Point X="219" Y="283" T="1681766152.889188"/>
    <Point X="217" Y="285" T="1681766152.896105"/>
    <Point X="217" Y="287" T="1681766152.897412"/>
    <Point X="213" Y="290" T="1681766152.9057631"/>
    <Point X="212" Y="292" T="1681766152.912065"/>
    <Point X="210" Y="295" T="1681766152.913491"/>
    <Point X="207" Y="298" T="1681766152.9222069"/>
    <Point X="205" Y="301" T="1681766152.92911"/>
    <Point X="201" Y="307" T="1681766152.941231"/>
    <Point X="199" Y="310" T="1681766152.946208"/>
    <Point X="198" Y="312" T="1681766152.94752"/>
    <Point X="194" Y="315" T="1681766152.955612"/>
    <Point X="193" Y="317" T="1681766152.961657"/>
    <Point X="192" Y="320" T="1681766152.966113"/>
    <Point X="190" Y="322" T="1681766152.971348"/>
    <Point X="189" Y="323" T="1681766152.973175"/>
    <Point X="188" Y="326" T="1681766152.9810848"/>
    <Point X="187" Y="327" T="1681766152.982823"/>
    <Point X="186" Y="329" T="1681766152.987982"/>
    <Point X="184" Y="331" T="1681766152.9883058"/>
    <Point X="180" Y="336" T="1681766153.006329"/>
    <Point X="177" Y="341" T="1681766153.034312"/>
    <Point X="177" Y="342" T="1681766153.0400808"/>
    <Point X="176" Y="343" T="1681766153.04587"/>
    <Point X="177" Y="342" T="1681766153.087359"/>
    <Point X="178" Y="342" T="1681766153.0940669"/>
    <Point X="179" Y="341" T="1681766153.096181"/>
    <Point X="182" Y="152" T="1681766154.720586"/>
    <Point X="180" Y="152" T="1681766154.729182"/>
    <Point X="179" Y="152" T="1681766154.74453"/>
    <Point X="179" Y="153" T="1681766154.7725692"/>
    <Point X="180" Y="153" T="1681766154.780428"/>
    <Point X="180" Y="154" T="1681766154.787374"/>
    <Point X="181" Y="155" T="1681766154.789147"/>
    <Point X="182" Y="155" T="1681766154.796431"/>
    <Point X="182" Y="156" T="1681766154.804186"/>
    <Point X="183" Y="156" T="1681766154.8068988"/>
    <Point X="183" Y="157" T="1681766154.816303"/>
    <Point X="184" Y="157" T="1681766154.8206851"/>
    <Point X="184" Y="158" T="1681766154.821903"/>
    <Point X="185" Y="158" T="1681766154.828955"/>
    <Point X="186" Y="158" T="1681766154.830542"/>
    <Point X="187" Y="159" T="1681766154.838836"/>
    <Point X="187" Y="160" T="1681766154.846733"/>
    <Point X="188" Y="160" T="1681766154.8494048"/>
    <Point X="189" Y="161" T="1681766154.8539798"/>
    <Point X="190" Y="162" T="1681766154.863559"/>
    <Point X="191" Y="163" T="1681766154.870615"/>
    <Point X="193" Y="163" T="1681766154.878842"/>
    <Point X="193" Y="164" T="1681766154.879849"/>
    <Point X="194" Y="165" T="1681766154.888133"/>
    <Point X="195" Y="166" T="1681766154.896609"/>
    <Point X="196" Y="167" T="1681766154.89939"/>
    <Point X="197" Y="167" T="1681766154.903852"/>
    <Point X="198" Y="168" T="1681766154.904991"/>
    <Point X="198" Y="169" T="1681766154.912931"/>
    <Point X="199" Y="170" T="1681766154.914091"/>
    <Point X="200" Y="171" T="1681766154.9213881"/>
    <Point X="201" Y="171" T="1681766154.922558"/>
    <Point X="202" Y="172" T="1681766154.9297438"/>
    <Point X="202" Y="173" T="1681766154.932804"/>
    <Point X="204" Y="175" T="1681766154.937452"/>
    <Point X="205" Y="176" T="1681766154.9456651"/>
    <Point X="206" Y="177" T="1681766154.947662"/>
    <Point X="209" Y="180" T="1681766154.955332"/>
    <Point X="210" Y="181" T="1681766154.961802"/>
    <Point X="211" Y="182" T="1681766154.9640079"/>
    <Point X="213" Y="183" T="1681766154.971436"/>
    <Point X="214" Y="184" T="1681766154.97181"/>
    <Point X="215" Y="185" T="1681766154.978614"/>
    <Point X="217" Y="186" T="1681766154.98042"/>
    <Point X="219" Y="188" T="1681766154.9888089"/>
    <Point X="220" Y="190" T="1681766154.9940321"/>
    <Point X="221" Y="191" T="1681766154.9996648"/>
    <Point X="223" Y="192" T="1681766155.003844"/>
    <Point X="224" Y="194" T="1681766155.0050619"/>
    <Point X="225" Y="196" T="1681766155.0125241"/>
    <Point X="227" Y="197" T="1681766155.0138721"/>
    <Point X="228" Y="198" T="1681766155.0209699"/>
    <Point X="229" Y="200" T="1681766155.0240839"/>
    <Point X="234" Y="204" T="1681766155.038713"/>
    <Point X="235" Y="206" T="1681766155.0402508"/>
    <Point X="237" Y="207" T="1681766155.045849"/>
    <Point X="239" Y="209" T="1681766155.0537012"/>
    <Point X="240" Y="210" T="1681766155.0538392"/>
    <Point X="242" Y="212" T="1681766155.055742"/>
    <Point X="243" Y="213" T="1681766155.061447"/>
    <Point X="244" Y="214" T="1681766155.063251"/>
    <Point X="247" Y="217" T="1681766155.0723462"/>
    <Point X="248" Y="219" T="1681766155.0777879"/>
    <Point X="250" Y="220" T="1681766155.087275"/>
    <Point X="251" Y="222" T="1681766155.087394"/>
    <Point X="254" Y="223" T="1681766155.0884328"/>
    <Point X="258" Y="228" T="1681766155.104952"/>
    <Point X="259" Y="230" T="1681766155.105906"/>
    <Point X="261" Y="231" T="1681766155.111439"/>
    <Point X="262" Y="233" T="1681766155.114076"/>
    <Point X="263" Y="234" T="1681766155.1201842"/>
    <Point X="265" Y="236" T="1681766155.122786"/>
    <Point X="268" Y="238" T="1681766155.1314619"/>
    <Point X="270" Y="241" T="1681766155.13836"/>
    <Point X="272" Y="243" T="1681766155.1442392"/>
    <Point X="273" Y="245" T="1681766155.149184"/>
    <Point X="274" Y="246" T="1681766155.153601"/>
    <Point X="276" Y="248" T="1681766155.157126"/>
    <Point X="277" Y="249" T="1681766155.161619"/>
    <Point X="281" Y="253" T="1681766155.172739"/>
    <Point X="283" Y="255" T="1681766155.178613"/>
    <Point X="285" Y="258" T="1681766155.1876218"/>
    <Point X="287" Y="259" T="1681766155.188769"/>
    <Point X="288" Y="261" T="1681766155.1947489"/>
    <Point X="289" Y="262" T="1681766155.1990662"/>
    <Point X="291" Y="263" T="1681766155.2039979"/>
    <Point X="292" Y="264" T="1681766155.2061062"/>
    <Point X="293" Y="266" T="1681766155.2116978"/>
    <Point X="295" Y="267" T="1681766155.214428"/>
    <Point X="296" Y="269" T="1681766155.221928"/>
    <Point X="298" Y="270" T="1681766155.222713"/>
    <Point X="299" Y="272" T="1681766155.229305"/>
    <Point X="300" Y="273" T="1681766155.23037"/>
    <Point X="302" Y="275" T="1681766155.2372239"/>
    <Point X="303" Y="276" T="1681766155.240997"/>
    <Point X="304" Y="277" T="1681766155.244989"/>
    <Point X="306" Y="280" T="1681766155.2497191"/>
    <Point X="307" Y="282" T="1681766155.255151"/>
    <Point X="309" Y="283" T="1681766155.261657"/>
    <Point X="310" Y="285" T="1681766155.26436"/>
    <Point X="311" Y="287" T="1681766155.2711968"/>
    <Point X="312" Y="288" T="1681766155.271625"/>
    <Point X="314" Y="289" T="1681766155.277378"/>
    <Point X="314" Y="290" T="1681766155.287723"/>
    <Point X="315" Y="291" T="1681766155.2880561"/>
    <Point X="317" Y="293" T="1681766155.288491"/>
    <Point X="318" Y="294" T="1681766155.29505"/>
    <Point X="319" Y="295" T="1681766155.299175"/>
    <Point X="320" Y="296" T="1681766155.3042402"/>
    <Point X="321" Y="298" T="1681766155.305141"/>
    <Point X="322" Y="299" T="1681766155.310462"/>
    <Point X="322" Y="300" T="1681766155.314202"/>
    <Point X="323" Y="301" T="1681766155.321922"/>
    <Point X="323" Y="302" T="1681766155.3228219"/>
    <Point X="324" Y="303" T="1681766155.327438"/>
    <Point X="325" Y="303" T="1681766155.331027"/>
    <Point X="325" Y="305" T="1681766155.337505"/>
    <Point X="326" Y="305" T="1681766155.3397639"/>
    <Point X="326" Y="306" T="1681766155.3445299"/>
    <Point X="326" Y="307" T="1681766155.347426"/>
    <Point X="326" Y="308" T="1681766155.3553762"/>
    <Point X="327" Y="309" T="1681766155.360393"/>
    <Point X="327" Y="310" T="1681766155.372342"/>
    <Point X="328" Y="310" T="1681766155.377384"/>
    <Point X="328" Y="311" T="1681766155.3875809"/>
    <Point X="329" Y="311" T="1681766155.390094"/>
    <Point X="329" Y="310" T="1681766155.457063"/>
    <Point X="329" Y="309" T="1681766155.470447"/>
    <Point X="329" Y="308" T="1681766155.47837"/>
    <Point X="329" Y="307" T="1681766155.488172"/>
    <Point X="329" Y="306" T="1681766155.489326"/>
    <Point X="329" Y="305" T="1681766155.503649"/>
    <Point X="329" Y="304" T="1681766155.504117"/>
    <Point X="329" Y="303" T="1681766155.5066109"/>
    <Point X="329" Y="302" T="1681766155.5099578"/>
    <Point X="329" Y="301" T="1681766155.521172"/>
    <Point X="329" Y="300" T="1681766155.523178"/>
    <Point X="329" Y="299" T="1681766155.527127"/>
    <Point X="329" Y="298" T="1681766155.5304298"/>
    <Point X="329" Y="297" T="1681766155.537985"/>
    <Point X="329" Y="296" T="1681766155.539728"/>
    <Point X="328" Y="295" T="1681766155.5437162"/>
    <Point X="328" Y="293" T="1681766155.549454"/>
    <Point X="327" Y="283" T="1681766155.579846"/>
    <Point X="326" Y="281" T="1681766155.585779"/>
    <Point X="326" Y="279" T="1681766155.5865269"/>
    <Point X="326" Y="277" T="1681766155.588819"/>
    <Point X="326" Y="275" T="1681766155.59439"/>
    <Point X="326" Y="273" T="1681766155.5995882"/>
    <Point X="326" Y="271" T="1681766155.604297"/>
    <Point X="325" Y="270" T="1681766155.6062238"/>
    <Point X="325" Y="267" T="1681766155.610759"/>
    <Point X="325" Y="265" T="1681766155.614379"/>
    <Point X="323" Y="260" T="1681766155.6292229"/>
    <Point X="322" Y="258" T="1681766155.6307032"/>
    <Point X="322" Y="256" T="1681766155.6372511"/>
    <Point X="322" Y="254" T="1681766155.6395679"/>
    <Point X="321" Y="252" T="1681766155.645809"/>
    <Point X="321" Y="250" T="1681766155.647524"/>
    <Point X="320" Y="248" T="1681766155.653861"/>
    <Point X="319" Y="246" T="1681766155.654551"/>
    <Point X="319" Y="245" T="1681766155.660248"/>
    <Point X="318" Y="243" T="1681766155.664103"/>
    <Point X="318" Y="241" T="1681766155.671148"/>
    <Point X="318" Y="239" T="1681766155.6722748"/>
    <Point X="318" Y="237" T="1681766155.677952"/>
    <Point X="317" Y="235" T="1681766155.6885161"/>
    <Point X="317" Y="233" T="1681766155.68865"/>
    <Point X="317" Y="232" T="1681766155.6895518"/>
    <Point X="317" Y="230" T="1681766155.6941829"/>
    <Point X="316" Y="227" T="1681766155.6995058"/>
    <Point X="316" Y="226" T="1681766155.7043781"/>
    <Point X="316" Y="223" T="1681766155.706764"/>
    <Point X="315" Y="221" T="1681766155.7111602"/>
    <Point X="315" Y="220" T="1681766155.714411"/>
    <Point X="315" Y="217" T="1681766155.7211258"/>
    <Point X="315" Y="215" T="1681766155.722137"/>
    <Point X="315" Y="213" T="1681766155.728058"/>
    <Point X="315" Y="212" T="1681766155.732794"/>
    <Point X="315" Y="210" T="1681766155.7370949"/>
    <Point X="315" Y="208" T="1681766155.737665"/>
    <Point X="315" Y="206" T="1681766155.744917"/>
    <Point X="315" Y="204" T="1681766155.747095"/>
    <Point X="315" Y="202" T="1681766155.754453"/>
    <Point X="315" Y="201" T="1681766155.75599"/>
    <Point X="315" Y="198" T="1681766155.7611141"/>
    <Point X="315" Y="197" T="1681766155.764302"/>
    <Point X="315" Y="195" T="1681766155.771171"/>
    <Point X="315" Y="193" T="1681766155.772461"/>
    <Point X="315" Y="191" T="1681766155.778081"/>
    <Point X="315" Y="189" T="1681766155.788013"/>
    <Point X="315" Y="187" T="1681766155.788141"/>
    <Point X="315" Y="185" T="1681766155.794158"/>
    <Point X="315" Y="183" T="1681766155.7975922"/>
    <Point X="315" Y="182" T="1681766155.8045492"/>
    <Point X="315" Y="180" T="1681766155.8062668"/>
    <Point X="315" Y="178" T="1681766155.811573"/>
    <Point X="315" Y="177" T="1681766155.813604"/>
    <Point X="314" Y="173" T="1681766155.822928"/>
    <Point X="314" Y="172" T="1681766155.827661"/>
    <Point X="314" Y="171" T="1681766155.831008"/>
    <Point X="314" Y="170" T="1681766155.8379478"/>
    <Point X="314" Y="168" T="1681766155.838269"/>
    <Point X="314" Y="167" T="1681766155.845321"/>
    <Point X="314" Y="165" T="1681766155.8477252"/>
    <Point X="314" Y="164" T="1681766155.854547"/>
    <Point X="314" Y="163" T="1681766155.855076"/>
    <Point X="314" Y="162" T="1681766155.861781"/>
    <Point X="314" Y="161" T="1681766155.8638132"/>
    <Point X="314" Y="160" T="1681766155.8716831"/>
    <Point X="313" Y="158" T="1681766155.872443"/>
    <Point X="313" Y="157" T="1681766155.880457"/>
    <Point X="313" Y="156" T="1681766155.888309"/>
    <Point X="313" Y="155" T="1681766155.889279"/>
    <Point X="313" Y="152" T="1681766155.9048781"/>
    <Point X="312" Y="152" T="1681766155.90536"/>
    <Point X="312" Y="151" T="1681766155.9161441"/>
    <Point X="312" Y="150" T="1681766155.928023"/>
    <Point X="311" Y="150" T="1681766155.953591"/>
    <Point X="311" Y="151" T="1681766155.979733"/>
    <Point X="310" Y="152" T="1681766155.986485"/>
    <Point X="309" Y="153" T="1681766155.997184"/>
    <Point X="308" Y="155" T="1681766156.006825"/>
    <Point X="308" Y="156" T="1681766156.011725"/>
    <Point X="308" Y="157" T="1681766156.0209322"/>
    <Point X="307" Y="158" T="1681766156.022766"/>
    <Point X="307" Y="159" T="1681766156.032654"/>
    <Point X="307" Y="160" T="1681766156.0385"/>
    <Point X="306" Y="161" T="1681766156.0388842"/>
    <Point X="306" Y="162" T="1681766156.045376"/>
    <Point X="305" Y="163" T="1681766156.0494158"/>
    <Point X="304" Y="164" T="1681766156.0542378"/>
    <Point X="303" Y="165" T="1681766156.0562072"/>
    <Point X="303" Y="166" T="1681766156.062017"/>
    <Point X="302" Y="167" T="1681766156.066229"/>
    <Point X="301" Y="169" T="1681766156.070993"/>
    <Point X="300" Y="171" T="1681766156.0723488"/>
    <Point X="296" Y="176" T="1681766156.088601"/>
    <Point X="295" Y="178" T="1681766156.09026"/>
    <Point X="293" Y="180" T="1681766156.0960891"/>
    <Point X="292" Y="182" T="1681766156.099478"/>
    <Point X="289" Y="184" T="1681766156.104301"/>
    <Point X="288" Y="186" T="1681766156.1060789"/>
    <Point X="287" Y="188" T="1681766156.111331"/>
    <Point X="284" Y="190" T="1681766156.116205"/>
    <Point X="283" Y="192" T="1681766156.121017"/>
    <Point X="281" Y="194" T="1681766156.1227908"/>
    <Point X="279" Y="196" T="1681766156.12927"/>
    <Point X="277" Y="198" T="1681766156.130761"/>
    <Point X="276" Y="201" T="1681766156.1379251"/>
    <Point X="273" Y="202" T="1681766156.1387641"/>
    <Point X="267" Y="210" T="1681766156.155242"/>
    <Point X="266" Y="212" T="1681766156.155967"/>
    <Point X="263" Y="214" T="1681766156.161209"/>
    <Point X="262" Y="216" T="1681766156.166137"/>
    <Point X="260" Y="218" T="1681766156.1709518"/>
    <Point X="258" Y="220" T="1681766156.171246"/>
    <Point X="256" Y="223" T="1681766156.178793"/>
    <Point X="254" Y="226" T="1681766156.180328"/>
    <Point X="250" Y="230" T="1681766156.188611"/>
    <Point X="248" Y="232" T="1681766156.195321"/>
    <Point X="246" Y="235" T="1681766156.197033"/>
    <Point X="244" Y="237" T="1681766156.204649"/>
    <Point X="243" Y="239" T="1681766156.205579"/>
    <Point X="240" Y="241" T="1681766156.212619"/>
    <Point X="239" Y="243" T="1681766156.213727"/>
    <Point X="237" Y="245" T="1681766156.222025"/>
    <Point X="235" Y="247" T="1681766156.222402"/>
    <Point X="233" Y="250" T="1681766156.228529"/>
    <Point X="232" Y="252" T="1681766156.232851"/>
    <Point X="230" Y="254" T="1681766156.237801"/>
    <Point X="228" Y="256" T="1681766156.241228"/>
    <Point X="227" Y="258" T="1681766156.245215"/>
    <Point X="224" Y="261" T="1681766156.246933"/>
    <Point X="223" Y="263" T="1681766156.254557"/>
    <Point X="221" Y="265" T="1681766156.255931"/>
    <Point X="220" Y="267" T="1681766156.264134"/>
    <Point X="218" Y="269" T="1681766156.2643929"/>
    <Point X="217" Y="271" T="1681766156.271202"/>
    <Point X="216" Y="273" T="1681766156.271774"/>
    <Point X="213" Y="276" T="1681766156.2782562"/>
    <Point X="213" Y="277" T="1681766156.282858"/>
    <Point X="211" Y="279" T="1681766156.2878568"/>
    <Point X="209" Y="281" T="1681766156.288897"/>
    <Point X="208" Y="283" T="1681766156.294654"/>
    <Point X="205" Y="286" T="1681766156.304645"/>
    <Point X="204" Y="288" T="1681766156.306392"/>
    <Point X="202" Y="289" T="1681766156.3121002"/>
    <Point X="201" Y="291" T="1681766156.321132"/>
    <Point X="199" Y="293" T="1681766156.321312"/>
    <Point X="198" Y="295" T="1681766156.322894"/>
    <Point X="197" Y="296" T="1681766156.3289971"/>
    <Point X="195" Y="297" T="1681766156.332876"/>
    <Point X="194" Y="299" T="1681766156.337989"/>
    <Point X="194" Y="301" T="1681766156.3394492"/>
    <Point X="192" Y="302" T="1681766156.347127"/>
    <Point X="190" Y="305" T="1681766156.35522"/>
    <Point X="189" Y="306" T="1681766156.35649"/>
    <Point X="189" Y="307" T="1681766156.361894"/>
    <Point X="187" Y="308" T="1681766156.3638961"/>
    <Point X="187" Y="309" T="1681766156.3722188"/>
    <Point X="186" Y="310" T="1681766156.372749"/>
    <Point X="186" Y="311" T="1681766156.380522"/>
    <Point X="185" Y="311" T="1681766156.380789"/>
    <Point X="184" Y="312" T="1681766156.38902"/>
    <Point X="184" Y="313" T="1681766156.4045131"/>
    <Point X="184" Y="314" T="1681766156.405257"/>
    <Point X="185" Y="314" T="1681766156.4397702"/>
    <Point X="186" Y="313" T="1681766156.445995"/>
</Gesture>
