<?xml version="1.0" ?>
<Gesture Name="pigtail03" Subject="user05" Number="03">
    <Point X="140" Y="362" T="1681797084.861104"/>
    <Point X="141" Y="362" T="1681797084.8642712"/>
    <Point X="142" Y="362" T="1681797084.86571"/>
    <Point X="143" Y="362" T="1681797084.8711538"/>
    <Point X="144" Y="362" T="1681797084.8811781"/>
    <Point X="145" Y="362" T="1681797084.882136"/>
    <Point X="146" Y="362" T="1681797084.8867059"/>
    <Point X="147" Y="362" T="1681797084.8906722"/>
    <Point X="150" Y="362" T="1681797084.8980532"/>
    <Point X="151" Y="361" T="1681797084.905011"/>
    <Point X="154" Y="360" T="1681797084.906888"/>
    <Point X="163" Y="357" T="1681797084.9241118"/>
    <Point X="165" Y="355" T="1681797084.931139"/>
    <Point X="169" Y="354" T="1681797084.932381"/>
    <Point X="172" Y="352" T="1681797084.9357598"/>
    <Point X="174" Y="351" T="1681797084.94066"/>
    <Point X="177" Y="349" T="1681797084.947764"/>
    <Point X="180" Y="347" T="1681797084.949057"/>
    <Point X="183" Y="345" T="1681797084.952619"/>
    <Point X="185" Y="343" T="1681797084.957398"/>
    <Point X="191" Y="340" T="1681797084.965971"/>
    <Point X="194" Y="338" T="1681797084.970287"/>
    <Point X="196" Y="337" T="1681797084.984618"/>
    <Point X="203" Y="333" T="1681797084.985493"/>
    <Point X="206" Y="331" T="1681797084.98732"/>
    <Point X="208" Y="328" T="1681797084.991168"/>
    <Point X="214" Y="324" T="1681797084.999151"/>
    <Point X="217" Y="322" T="1681797085.003309"/>
    <Point X="220" Y="319" T="1681797085.0069618"/>
    <Point X="222" Y="317" T="1681797085.015742"/>
    <Point X="225" Y="315" T="1681797085.0162508"/>
    <Point X="228" Y="312" T="1681797085.020811"/>
    <Point X="231" Y="310" T="1681797085.026736"/>
    <Point X="233" Y="308" T="1681797085.031747"/>
    <Point X="237" Y="305" T="1681797085.032415"/>
    <Point X="239" Y="302" T="1681797085.037225"/>
    <Point X="241" Y="300" T="1681797085.040666"/>
    <Point X="244" Y="297" T="1681797085.04815"/>
    <Point X="247" Y="295" T="1681797085.048612"/>
    <Point X="249" Y="292" T="1681797085.052157"/>
    <Point X="252" Y="289" T="1681797085.057055"/>
    <Point X="254" Y="287" T="1681797085.065522"/>
    <Point X="256" Y="284" T="1681797085.0662022"/>
    <Point X="259" Y="281" T="1681797085.0698419"/>
    <Point X="261" Y="278" T="1681797085.074592"/>
    <Point X="263" Y="276" T="1681797085.0810828"/>
    <Point X="266" Y="272" T="1681797085.082243"/>
    <Point X="267" Y="270" T="1681797085.085679"/>
    <Point X="270" Y="267" T="1681797085.0919628"/>
    <Point X="274" Y="262" T="1681797085.099395"/>
    <Point X="275" Y="259" T="1681797085.1031098"/>
    <Point X="278" Y="256" T="1681797085.1064699"/>
    <Point X="279" Y="253" T="1681797085.1144488"/>
    <Point X="281" Y="251" T="1681797085.1164758"/>
    <Point X="282" Y="248" T="1681797085.119601"/>
    <Point X="283" Y="245" T="1681797085.12406"/>
    <Point X="286" Y="240" T="1681797085.1328719"/>
    <Point X="287" Y="238" T="1681797085.13664"/>
    <Point X="289" Y="235" T="1681797085.141461"/>
    <Point X="290" Y="233" T="1681797085.1475441"/>
    <Point X="291" Y="230" T="1681797085.1488872"/>
    <Point X="292" Y="227" T="1681797085.154211"/>
    <Point X="293" Y="225" T="1681797085.158736"/>
    <Point X="294" Y="222" T="1681797085.1661499"/>
    <Point X="294" Y="220" T="1681797085.166444"/>
    <Point X="294" Y="218" T="1681797085.169544"/>
    <Point X="295" Y="216" T="1681797085.1739788"/>
    <Point X="295" Y="214" T="1681797085.176917"/>
    <Point X="296" Y="213" T="1681797085.182457"/>
    <Point X="296" Y="211" T="1681797085.188221"/>
    <Point X="296" Y="209" T="1681797085.190998"/>
    <Point X="296" Y="208" T="1681797085.198926"/>
    <Point X="296" Y="206" T="1681797085.199317"/>
    <Point X="296" Y="204" T="1681797085.203538"/>
    <Point X="296" Y="202" T="1681797085.207053"/>
    <Point X="295" Y="200" T="1681797085.214717"/>
    <Point X="295" Y="198" T="1681797085.221057"/>
    <Point X="294" Y="196" T="1681797085.224988"/>
    <Point X="294" Y="193" T="1681797085.232926"/>
    <Point X="294" Y="192" T="1681797085.237084"/>
    <Point X="293" Y="190" T="1681797085.2398489"/>
    <Point X="293" Y="188" T="1681797085.24852"/>
    <Point X="293" Y="187" T="1681797085.2530282"/>
    <Point X="292" Y="186" T="1681797085.25747"/>
    <Point X="290" Y="184" T="1681797085.266516"/>
    <Point X="289" Y="183" T="1681797085.2698328"/>
    <Point X="287" Y="182" T="1681797085.281325"/>
    <Point X="286" Y="181" T="1681797085.282149"/>
    <Point X="285" Y="181" T="1681797085.28729"/>
    <Point X="284" Y="180" T="1681797085.290709"/>
    <Point X="282" Y="180" T="1681797085.298688"/>
    <Point X="280" Y="180" T="1681797085.303261"/>
    <Point X="278" Y="179" T="1681797085.307532"/>
    <Point X="277" Y="179" T="1681797085.314831"/>
    <Point X="275" Y="179" T="1681797085.315535"/>
    <Point X="274" Y="179" T="1681797085.320443"/>
    <Point X="272" Y="179" T="1681797085.324758"/>
    <Point X="268" Y="180" T="1681797085.332567"/>
    <Point X="267" Y="181" T="1681797085.336451"/>
    <Point X="265" Y="181" T="1681797085.340786"/>
    <Point X="263" Y="182" T="1681797085.3481169"/>
    <Point X="262" Y="183" T="1681797085.349122"/>
    <Point X="260" Y="183" T="1681797085.352722"/>
    <Point X="258" Y="184" T="1681797085.357174"/>
    <Point X="255" Y="186" T="1681797085.366276"/>
    <Point X="252" Y="187" T="1681797085.370185"/>
    <Point X="251" Y="188" T="1681797085.3729038"/>
    <Point X="249" Y="189" T="1681797085.3808541"/>
    <Point X="247" Y="190" T="1681797085.382178"/>
    <Point X="245" Y="192" T="1681797085.385537"/>
    <Point X="244" Y="193" T="1681797085.3906822"/>
    <Point X="242" Y="195" T="1681797085.398612"/>
    <Point X="241" Y="196" T="1681797085.39896"/>
    <Point X="239" Y="198" T="1681797085.402787"/>
    <Point X="237" Y="200" T="1681797085.407327"/>
    <Point X="236" Y="202" T="1681797085.4146261"/>
    <Point X="234" Y="204" T="1681797085.416478"/>
    <Point X="233" Y="206" T="1681797085.4211452"/>
    <Point X="232" Y="208" T="1681797085.423172"/>
    <Point X="230" Y="211" T="1681797085.431295"/>
    <Point X="229" Y="213" T="1681797085.432988"/>
    <Point X="223" Y="224" T="1681797085.456963"/>
    <Point X="222" Y="227" T="1681797085.4572742"/>
    <Point X="222" Y="229" T="1681797085.4646468"/>
    <Point X="221" Y="231" T="1681797085.465472"/>
    <Point X="221" Y="233" T="1681797085.470239"/>
    <Point X="220" Y="236" T="1681797085.474314"/>
    <Point X="219" Y="241" T="1681797085.4823492"/>
    <Point X="218" Y="243" T="1681797085.485665"/>
    <Point X="218" Y="245" T="1681797085.49063"/>
    <Point X="218" Y="248" T="1681797085.498553"/>
    <Point X="218" Y="251" T="1681797085.515574"/>
    <Point X="218" Y="258" T="1681797085.51575"/>
    <Point X="218" Y="261" T="1681797085.5184052"/>
    <Point X="218" Y="263" T="1681797085.519221"/>
    <Point X="218" Y="265" T="1681797085.524771"/>
    <Point X="218" Y="271" T="1681797085.532393"/>
    <Point X="218" Y="273" T="1681797085.537193"/>
    <Point X="218" Y="276" T="1681797085.540543"/>
    <Point X="219" Y="280" T="1681797085.549451"/>
    <Point X="219" Y="283" T="1681797085.553934"/>
    <Point X="221" Y="285" T="1681797085.557544"/>
    <Point X="222" Y="289" T="1681797085.566777"/>
    <Point X="223" Y="291" T="1681797085.569664"/>
    <Point X="225" Y="293" T="1681797085.574202"/>
    <Point X="225" Y="295" T="1681797085.581496"/>
    <Point X="227" Y="297" T="1681797085.582607"/>
    <Point X="229" Y="299" T="1681797085.585747"/>
    <Point X="229" Y="301" T="1681797085.5907578"/>
    <Point X="233" Y="305" T="1681797085.5994"/>
    <Point X="234" Y="306" T="1681797085.603422"/>
    <Point X="236" Y="308" T="1681797085.606832"/>
    <Point X="237" Y="310" T="1681797085.615177"/>
    <Point X="238" Y="312" T="1681797085.6154392"/>
    <Point X="241" Y="313" T="1681797085.620149"/>
    <Point X="242" Y="314" T="1681797085.624235"/>
    <Point X="245" Y="318" T="1681797085.633368"/>
    <Point X="248" Y="320" T="1681797085.636466"/>
    <Point X="249" Y="321" T="1681797085.6409469"/>
    <Point X="252" Y="322" T="1681797085.64849"/>
    <Point X="253" Y="324" T="1681797085.6489758"/>
    <Point X="256" Y="325" T="1681797085.6541529"/>
    <Point X="258" Y="326" T="1681797085.656681"/>
    <Point X="262" Y="329" T="1681797085.666369"/>
    <Point X="264" Y="331" T="1681797085.6693451"/>
    <Point X="267" Y="332" T="1681797085.673745"/>
    <Point X="271" Y="334" T="1681797085.681674"/>
    <Point X="274" Y="335" T="1681797085.686778"/>
    <Point X="277" Y="336" T="1681797085.690955"/>
    <Point X="282" Y="337" T="1681797085.6997042"/>
    <Point X="285" Y="338" T="1681797085.7040691"/>
    <Point X="288" Y="339" T="1681797085.707079"/>
    <Point X="294" Y="341" T="1681797085.715852"/>
    <Point X="297" Y="342" T="1681797085.720543"/>
    <Point X="301" Y="342" T="1681797085.7241962"/>
    <Point X="307" Y="344" T="1681797085.733977"/>
    <Point X="311" Y="345" T="1681797085.7416792"/>
    <Point X="314" Y="345" T="1681797085.743592"/>
    <Point X="317" Y="345" T="1681797085.7481558"/>
    <Point X="321" Y="346" T="1681797085.750251"/>
    <Point X="324" Y="346" T="1681797085.753118"/>
    <Point X="328" Y="346" T="1681797085.75738"/>
    <Point X="332" Y="346" T="1681797085.765528"/>
    <Point X="336" Y="347" T="1681797085.766345"/>
    <Point X="339" Y="347" T="1681797085.76897"/>
    <Point X="343" Y="347" T="1681797085.7744582"/>
    <Point X="346" Y="347" T="1681797085.7814841"/>
    <Point X="350" Y="347" T="1681797085.783193"/>
    <Point X="354" Y="346" T="1681797085.786332"/>
    <Point X="357" Y="346" T="1681797085.791518"/>
    <Point X="361" Y="345" T="1681797085.798731"/>
    <Point X="364" Y="345" T="1681797085.798978"/>
    <Point X="368" Y="345" T="1681797085.803791"/>
    <Point X="371" Y="344" T="1681797085.807007"/>
    <Point X="377" Y="342" T="1681797085.815907"/>
    <Point X="380" Y="342" T="1681797085.8199492"/>
    <Point X="383" Y="341" T="1681797085.824091"/>
    <Point X="384" Y="340" T="1681797085.831435"/>
    <Point X="387" Y="340" T="1681797085.8321002"/>
    <Point X="390" Y="339" T="1681797085.836024"/>
    <Point X="391" Y="338" T="1681797085.840596"/>
    <Point X="395" Y="336" T="1681797085.849076"/>
</Gesture>
